sdmetrics/__init__.py
sdmetrics/_utils_metadata.py
sdmetrics/base.py
sdmetrics/demos.py
sdmetrics/errors.py
sdmetrics/goal.py
sdmetrics/utils.py
sdmetrics/visualization.py
sdmetrics/warnings.py
sdmetrics/column_pairs/__init__.py
sdmetrics/column_pairs/base.py
sdmetrics/column_pairs/statistical/__init__.py
sdmetrics/column_pairs/statistical/cardinality_boundary_adherence.py
sdmetrics/column_pairs/statistical/contingency_similarity.py
sdmetrics/column_pairs/statistical/correlation_similarity.py
sdmetrics/column_pairs/statistical/inter_row_msas.py
sdmetrics/column_pairs/statistical/kl_divergence.py
sdmetrics/column_pairs/statistical/referential_integrity.py
sdmetrics/column_pairs/statistical/statistic_msas.py
sdmetrics/demos/multi_table/metadata.json
sdmetrics/demos/multi_table/sessions_real.csv
sdmetrics/demos/multi_table/sessions_synthetic.csv
sdmetrics/demos/multi_table/transactions_real.csv
sdmetrics/demos/multi_table/transactions_synthetic.csv
sdmetrics/demos/multi_table/users_real.csv
sdmetrics/demos/multi_table/users_synthetic.csv
sdmetrics/demos/single_table/metadata.json
sdmetrics/demos/single_table/real.csv
sdmetrics/demos/single_table/synthetic.csv
sdmetrics/demos/timeseries/metadata.json
sdmetrics/demos/timeseries/real.csv
sdmetrics/demos/timeseries/synthetic.csv
sdmetrics/multi_table/README.md
sdmetrics/multi_table/__init__.py
sdmetrics/multi_table/base.py
sdmetrics/multi_table/multi_single_table.py
sdmetrics/multi_table/detection/__init__.py
sdmetrics/multi_table/detection/base.py
sdmetrics/multi_table/detection/parent_child.py
sdmetrics/multi_table/statistical/__init__.py
sdmetrics/multi_table/statistical/cardinality_shape_similarity.py
sdmetrics/multi_table/statistical/cardinality_statistic_similarity.py
sdmetrics/reports/__init__.py
sdmetrics/reports/base_report.py
sdmetrics/reports/utils.py
sdmetrics/reports/multi_table/__init__.py
sdmetrics/reports/multi_table/base_multi_table_report.py
sdmetrics/reports/multi_table/diagnostic_report.py
sdmetrics-0.27.0.dist-info/licenses/LICENSE
sdmetrics-0.27.0.dist-info/METADATA
sdmetrics-0.27.0.dist-info/WHEEL
sdmetrics-0.27.0.dist-info/entry_points.txt
sdmetrics-0.27.0.dist-info/top_level.txt
sdmetrics-0.27.0.dist-info/RECORD
