Metadata-Version: 2.4
Name: sdmetrics
Version: 0.27.0
Summary: Metrics for Synthetic Data Generation Projects
Author-email: MIT Data To AI Lab <dailabmit@gmail.com>
License: MIT license
Project-URL: Source Code, https://github.com/sdv-dev/SDMetrics
Project-URL: Issue Tracker, https://github.com/sdv-dev/SDMetrics/issues
Project-URL: Changes, https://github.com/sdv-dev/SDMetrics/blob/main/HISTORY.md
Project-URL: Twitter, https://twitter.com/sdv_dev
Project-URL: Chat, https://bit.ly/sdv-slack-invite
Keywords: sdmetrics,SDMetrics
Classifier: Development Status :: 2 - Pre-Alpha
Classifier: Intended Audience :: Developers
Classifier: License :: OSI Approved :: MIT License
Classifier: Natural Language :: English
Classifier: Programming Language :: Python :: 3
Classifier: Programming Language :: Python :: 3.9
Classifier: Programming Language :: Python :: 3.10
Classifier: Programming Language :: Python :: 3.11
Classifier: Programming Language :: Python :: 3.12
Classifier: Programming Language :: Python :: 3.13
Classifier: Programming Language :: Python :: 3.14
Requires-Python: <3.15,>=3.9
License-File: LICENSE
Requires-Dist: numpy>=1.22.2; python_version < "3.10"
Requires-Dist: numpy>=1.24.0; python_version >= "3.10" and python_version < "3.12"
Requires-Dist: numpy>=1.26.0; python_version >= "3.12" and python_version < "3.13"
Requires-Dist: numpy>=2.1.0; python_version >= "3.13" and python_version < "3.14"
Requires-Dist: numpy>=2.3.2; python_version >= "3.14"
Requires-Dist: pandas<3.0.0,>=1.4.0; python_version < "3.11"
Requires-Dist: pandas<3.0.0,>=1.5.0; python_version >= "3.11" and python_version < "3.12"
Requires-Dist: pandas<3.0.0,>=2.1.1; python_version >= "3.12" and python_version < "3.13"
Requires-Dist: pandas<3.0.0,>=2.2.3; python_version >= "3.13" and python_version < "3.14"
Requires-Dist: pandas<3.0.0,>=2.3.3; python_version >= "3.14"
Requires-Dist: scikit-learn>=1.0.2; python_version < "3.10"
Requires-Dist: scikit-learn>=1.1.0; python_version >= "3.10" and python_version < "3.11"
Requires-Dist: scikit-learn>=1.1.3; python_version >= "3.11" and python_version < "3.12"
Requires-Dist: scikit-learn>=1.3.1; python_version >= "3.12" and python_version < "3.13"
Requires-Dist: scikit-learn>=1.5.2; python_version >= "3.13" and python_version < "3.14"
Requires-Dist: scikit-learn>=1.8.0; python_version >= "3.14"
Requires-Dist: scipy>=1.7.3; python_version < "3.10"
Requires-Dist: scipy>=1.9.2; python_version >= "3.10" and python_version < "3.12"
Requires-Dist: scipy>=1.12.0; python_version >= "3.12" and python_version < "3.13"
Requires-Dist: scipy>=1.14.1; python_version >= "3.13" and python_version < "3.14"
Requires-Dist: scipy>=1.16.1; python_version >= "3.14"
Requires-Dist: copulas>=0.12.1; python_version < "3.14"
Requires-Dist: copulas>=0.14.0; python_version >= "3.14"
Requires-Dist: tqdm>=4.29
Requires-Dist: plotly>=5.19.0
Provides-Extra: torch
Requires-Dist: torch>=1.8.0; python_version < "3.10" and extra == "torch"
Requires-Dist: torch>=2.0.0; (python_version >= "3.10" and python_version < "3.12") and extra == "torch"
Requires-Dist: torch>=2.2.0; (python_version >= "3.12" and python_version < "3.13") and extra == "torch"
Requires-Dist: torch>=2.6.0; (python_version >= "3.13" and python_version < "3.14") and extra == "torch"
Requires-Dist: torch>=2.8.0; python_version >= "3.14" and extra == "torch"
Provides-Extra: pomegranate
Requires-Dist: pomegranate<2.0,>=1.1.2; extra == "pomegranate"
Provides-Extra: xgboost
Requires-Dist: xgboost>=2.1.3; python_version < "3.10" and extra == "xgboost"
Requires-Dist: xgboost>=3.0.0; python_version >= "3.10" and extra == "xgboost"
Provides-Extra: test
Requires-Dist: sdmetrics[pomegranate,torch,xgboost]; extra == "test"
Requires-Dist: pytest>=6.2.5; extra == "test"
Requires-Dist: pytest-cov>=2.6.0; extra == "test"
Requires-Dist: pytest-rerunfailures<17,>=10.3; extra == "test"
Requires-Dist: jupyter<2,>=1.0.0; extra == "test"
Requires-Dist: tomli<3,>=2.0.0; extra == "test"
Requires-Dist: invoke; extra == "test"
Requires-Dist: pytest-runner>=2.11.1; extra == "test"
Provides-Extra: readme
Requires-Dist: rundoc<0.5,>=0.4.3; extra == "readme"
Provides-Extra: dev
Requires-Dist: sdmetrics[test,torch]; extra == "dev"
Requires-Dist: build<2,>=1.0.0; extra == "dev"
Requires-Dist: bump-my-version>=0.18.3; extra == "dev"
Requires-Dist: pip>=9.0.1; extra == "dev"
Requires-Dist: watchdog<5,>=1.0.1; extra == "dev"
Requires-Dist: ruff<1,>=0.3.2; extra == "dev"
Requires-Dist: twine>=1.10.0; extra == "dev"
Requires-Dist: wheel>=0.30.0; extra == "dev"
Requires-Dist: packaging<25,>=20; extra == "dev"
Requires-Dist: coverage<8,>=4.5.12; extra == "dev"
Dynamic: license-file
